image_processing_dio_amanda/__init__.py
image_processing_dio_amanda/processing/__init__.py
image_processing_dio_amanda/processing/combination.py
image_processing_dio_amanda/processing/transformation.py
image_processing_dio_amanda/utils/__init__.py
image_processing_dio_amanda/utils/io.py
image_processing_dio_amanda/utils/plot.py
image_processing_dio_amanda-0.0.1.dist-info/METADATA
image_processing_dio_amanda-0.0.1.dist-info/WHEEL
image_processing_dio_amanda-0.0.1.dist-info/top_level.txt
image_processing_dio_amanda-0.0.1.dist-info/RECORD
