Metadata-Version: 2.4
Name: image-processing_dio_amanda
Version: 0.0.1
Summary: Image processing package
Home-page: https://github.com/Carmo-Amanda/image-processing-package.git
Author: Carmo-Amanda
Author-email: aaocarmo@gmail.com
Requires-Python: >=3.8
Dynamic: author
Dynamic: author-email
Dynamic: description
Dynamic: description-content-type
Dynamic: home-page
Dynamic: requires-python
Dynamic: summary
